{
  "posts": [
    {
      "id": "1731579746552",
      "title": "Madaraka Day Afterparty",
      "image_url": "https://img.freepik.com/free-psd/club-dj-party-flyer-social-media-post_505751-4534.jpg?semt=ais_hybrid",
      "content": "Welcome to our outdoor afterparty bonfire!",
      "author": "Mashup",
      "comments": []
    },
    {
      "title": "Black Friday",
      "image_url": "https://img.freepik.com/free-photo/top-view-black-friday-assortment-black-background_23-2148665583.jpg?semt=ais_hybrid",
      "content": "Get your Laptop this November!!",
      "author": "Mashup",
      "id": "1731605740504"
    },
    {
      "id": "1731612040569",
      "title": "Tricylcling",
      "image_url": "https://img.freepik.com/free-photo/dirt-bike-rider-participating-races-circuits-adventure-thrill-with-motorcycle_23-2151482672.jpg?semt=ais_hybrid",
      "content": "Extra-ordinary championship",
      "author": "Socademy",
      "comments": []
    },
    {
      "title": "Wedding Show",
      "image_url": "https://img.freepik.com/free-photo/high-angle-shot-old-shoes-bride-groom-standing-dry-grass_181624-28371.jpg?semt=ais_hybrid",
      "content": "Save the date for the big wedding day.....",
      "author": "Wedventure",
      "id": "1731612157335"
    },
    {
      "title": "End of Season Games",
      "image_url": "https://img.freepik.com/free-vector/hand-drawn-sports-team-raffle-ticke_742173-3578.jpg?semt=ais_hybrid",
      "content": "Secure your tickets early at a discount of 10%.",
      "author": "Socademy",
      "id": "1731649875598"
    },
    {
      "title": "Bush Party",
      "image_url": "https://img.freepik.com/free-photo/front-view-friends-having-cocktails_23-2150244915.jpg?semt=ais_hybrid",
      "content": "Welcome to Bush Party 24 Edition",
      "author": "Tulo",
      "id": "1731650616628"
    },
    {
      "id": "1731650778119",
      "title": "Closing Ceremony",
      "image_url": "https://img.freepik.com/free-vector/grand-opening_52683-8448.jpg?semt=ais_hybrid",
      "content": "welcome All",
      "author": "Tulo",
      "comments": []
    },
    {
      "id": "1731650944727",
      "title": "Secondary Graduation",
      "image_url": "https://img.freepik.com/free-psd/congratulations-graduates-illustration_23-2151408110.jpg?semt=ais_hybrid",
      "content": "Welcome",
      "author": "Tulo",
      "comments": []
    },
    {
      "id": "1731651166737",
      "title": "Anniversary",
      "image_url": "https://img.freepik.com/free-psd/minimal-template-wedding-banner_23-2148382909.jpg?semt=ais_hybrid",
      "content": "Welcome",
      "author": "Mercy",
      "comments": []
    },
    {
      "id": "1731651372016",
      "title": "Bonfire Party",
      "image_url": "https://img.freepik.com/free-photo/bonfire-beach_144627-2587.jpg?semt=ais_hybrid",
      "content": "Keep the date ",
      "author": "Mercy",
      "comments": []
    },
    {
      "id": "1731651453681",
      "title": "Adventure",
      "image_url": "https://img.freepik.com/free-photo/rear-view-back-young-asian-hiking-man-standing-riseup-hands-with-happy-peak-rocky-mountain-copy-space_1150-57186.jpg?semt=ais_hybrid",
      "content": "Soon than before",
      "author": "Mercy",
      "comments": []
    }
  ],
  "users": [
    {
      "id": "23e3",
      "username": "Redhut",
      "image_url": "https://img.freepik.com/premium-vector/young-man-portrait-with-rounded-colored-frame-icon_24911-7122.jpg?semt=ais_hybrid",
      "password": "user.101",
      "isAdmin": false,
      "bookedEvents": [
        "1731605740504",
        "1731612157335"
      ]
    },
    {
      "id": "5170",
      "username": "Blackmask",
      "image_url": "https://img.freepik.com/premium-vector/cute-animal-playing-soccer-ball-cartoon-vector-icon-illustration-animal-sport-icon-concept-isolated_844724-3709.jpg?semt=ais_hybrid",
      "password": "user.101",
      "isAdmin": false,
      "bookedEvents": []
    },
    {
      "id": "3067",
      "username": "Mashup",
      "image_url": "https://img.freepik.com/premium-photo/flamingo-armor-head-banner-picture-surrealism-art-collage-modern-look-magazine-style-poster-advertising-mixed-media-inspiration-creativity-bright-colors-copy-space_99433-8370.jpg?semt=ais_hybrid",
      "password": "user.101",
      "isAdmin": true,
      "postedEvents": [
        "1731579746552",
        "1731605740504"
      ]
    },
    {
      "id": "9507",
      "username": "Wedventure",
      "image_url": "https://img.freepik.com/free-vector/gradient-upcoming-events-label-collection_23-2149481564.jpg?semt=ais_hybrid",
      "password": "user.101",
      "isAdmin": true,
      "postedEvents": [
        "1731612157335"
      ]
    },
    {
      "id": "d721",
      "username": "Socademy",
      "image_url": "https://img.freepik.com/premium-vector/afootball_193274-34255.jpg?semt=ais_hybrid",
      "password": "user.101",
      "isAdmin": true,
      "postedEvents": [
        "1731612040569",
        "1731649875598"
      ]
    },
    {
      "id": "daa4",
      "username": "G123",
      "image_url": "https://img.freepik.com/free-vector/mysterious-mafia-man-smoking-cigarette_52683-34828.jpg?semt=ais_hybrid",
      "password": "user.101",
      "isAdmin": false,
      "bookedEvents": []
    },
    {
      "id": "e32d",
      "username": "Tulo",
      "image_url": "https://img.freepik.com/free-vector/professional-tiktok-profile-picture_742173-5866.jpg?semt=ais_hybrid",
      "password": "1234",
      "isAdmin": true,
      "postedEvents": [
        "1731650616628",
        "1731650778119",
        "1731650944727"
      ]
    },
    {
      "id": "d600",
      "username": "Tulo",
      "image_url": "https://img.freepik.com/free-photo/front-view-man-with-beard-posing_23-2149438512.jpg?semt=ais_hybrid",
      "password": "1234",
      "isAdmin": false
    },
    {
      "id": "60b5",
      "username": "Mercy",
      "image_url": "https://img.freepik.com/premium-photo/portrait-curlyhaired-woman-with-glasses-looking-into-camera-isolated-white-background_283470-8491.jpg?semt=ais_hybrid",
      "password": "1234",
      "isAdmin": true,
      "postedEvents": [
        "1731651166737",
        "1731651372016",
        "1731651453681"
      ]
    },
    {
      "id": "b446",
      "username": "Chemoget",
      "image_url": "https://img.freepik.com/free-photo/serious-self-assured-man-with-curly-hair-looks-with-concentrated-expression-dressed-white-shirt-listens-attentively_273609-17084.jpg?semt=ais_hybrid",
      "password": "1234",
      "isAdmin": false,
      "bookedEvents": [
        "1731612157335"
      ]
    }
  ]
}
